lcore/__init__.py
lcore/client.py
lcore/device.py
lcore/did.py
lcore/models.py
lcore_sdk-0.1.0.dist-info/METADATA
lcore_sdk-0.1.0.dist-info/WHEEL
lcore_sdk-0.1.0.dist-info/RECORD
