Metadata-Version: 2.4
Name: lcore-sdk
Version: 0.1.0
Summary: Python SDK for L{CORE} - Privacy-preserving IoT attestation layer
Project-URL: Homepage, https://github.com/Modern-Society-Labs/lcore-sdk
Project-URL: Documentation, https://github.com/Modern-Society-Labs/lcore-sdk/tree/main/docs
Project-URL: Repository, https://github.com/Modern-Society-Labs/lcore-sdk
Author: Modern Society Labs
License-Expression: MIT
Keywords: attestation,blockchain,cartesi,did,iot,web3
Classifier: Development Status :: 4 - Beta
Classifier: Intended Audience :: Developers
Classifier: License :: OSI Approved :: MIT License
Classifier: Programming Language :: Python :: 3
Classifier: Programming Language :: Python :: 3.9
Classifier: Programming Language :: Python :: 3.10
Classifier: Programming Language :: Python :: 3.11
Classifier: Programming Language :: Python :: 3.12
Classifier: Topic :: Internet :: WWW/HTTP
Classifier: Topic :: Security :: Cryptography
Classifier: Topic :: Software Development :: Libraries :: Python Modules
Requires-Python: >=3.9
Requires-Dist: base58>=2.1.0
Requires-Dist: coincurve>=18.0.0
Requires-Dist: httpx>=0.25.0
Requires-Dist: pynacl>=1.5.0
Provides-Extra: dev
Requires-Dist: pytest-asyncio>=0.21.0; extra == 'dev'
Requires-Dist: pytest-httpx>=0.22.0; extra == 'dev'
Requires-Dist: pytest>=7.0.0; extra == 'dev'
